LICENSE
MANIFEST.in
README.rst
setup.py
iesugrace_django_polls.egg-info/PKG-INFO
iesugrace_django_polls.egg-info/SOURCES.txt
iesugrace_django_polls.egg-info/dependency_links.txt
iesugrace_django_polls.egg-info/top_level.txt
mysite/.gitignore
mysite/manage.py
mysite/populate.py
mysite/mysite/__init__.py
mysite/mysite/settings.py
mysite/mysite/urls.py
mysite/mysite/wsgi.py
mysite/polls/__init__.py
mysite/polls/admin.py
mysite/polls/apps.py
mysite/polls/forms.py
mysite/polls/models.py
mysite/polls/tests.py
mysite/polls/urls.py
mysite/polls/views.py
mysite/polls/migrations/0001_initial.py
mysite/polls/migrations/0002_auto_20180111_0705.py
mysite/polls/migrations/0003_user.py
mysite/polls/migrations/__init__.py
mysite/polls/static/css/style.css
mysite/polls/templates/polls/base.html
mysite/polls/templates/polls/detail.html
mysite/polls/templates/polls/index.html
mysite/polls/templates/polls/login.html
mysite/polls/templates/polls/results.html
mysite/polls/templates/polls/signup.html
mysite/polls/templatetags/__init__.py
mysite/polls/templatetags/myfilters.py