Metadata-Version: 1.1
Name: iesugrace-django-polls
Version: 0.2
Summary: A simple Django app to conduct Web-based polls.
Home-page: https://github.com/iesugrace/iesugrace-django-polls
Author: iesugrace
Author-email: iesugrace@gmail.com
License: GPLv3
Download-URL: https://github.com/iesugrace/iesugrace-django-polls/archive/0.2.tar.gz
Platform: UNKNOWN
Classifier: Environment :: Web Environment
Classifier: Framework :: Django
Classifier: Framework :: Django :: 1.11
Classifier: Intended Audience :: Developers
Classifier: License :: OSI Approved :: GNU General Public License v3 (GPLv3)
Classifier: Operating System :: OS Independent
Classifier: Programming Language :: Python
Classifier: Programming Language :: Python :: 3.5
Classifier: Programming Language :: Python :: 3.6
Classifier: Topic :: Internet :: WWW/HTTP
Classifier: Topic :: Internet :: WWW/HTTP :: Dynamic Content
